{
  "name": "security-center",
  "type": "module",
  "category": "security",
  "title": "Security Center",
  "description": "Unified security center for workspace posture, access, API keys, events, and controls.",
  "dependencies": [],
  "devDependencies": [],
  "registryDependencies": [],
  "env": [],
  "files": [],
  "status": "stub",
  "maintenance": {
    "skills": [
      "security-center"
    ],
    "rules": [
      "define-source-payload-before-ready",
      "document-install-order"
    ]
  }
}
