{
  "$schema": "https://ui.shadcn.com/schema/registry-item.json",
  "name": "orgs-rbac",
  "type": "registry:item",
  "title": "Organizations and RBAC",
  "description": "Organization switcher, roles, permissions, invitations, and member management.",
  "dependencies": [],
  "devDependencies": [],
  "registryDependencies": [],
  "files": [],
  "meta": {
    "category": "auth",
    "env": [],
    "status": "planned",
    "agents": {
      "skills": [
        "orgs-rbac"
      ],
      "rules": [
        "document-invariants",
        "verify-before-release"
      ]
    }
  }
}
